PythonProgrammingP/__init__.py
PythonProgrammingP/statistics.py
pythonprogrammingp-0.0.1.dist-info/licenses/LICENSE
pythonprogrammingp-0.0.1.dist-info/METADATA
pythonprogrammingp-0.0.1.dist-info/WHEEL
pythonprogrammingp-0.0.1.dist-info/top_level.txt
pythonprogrammingp-0.0.1.dist-info/RECORD
